bytedance_shoots_tokopedia_lib/__init__.py
bytedance_shoots_tokopedia_lib-0.0.1.dist-info/METADATA
bytedance_shoots_tokopedia_lib-0.0.1.dist-info/WHEEL
bytedance_shoots_tokopedia_lib-0.0.1.dist-info/top_level.txt
bytedance_shoots_tokopedia_lib-0.0.1.dist-info/RECORD
