Metadata-Version: 2.1
Name: bytedance-shoots-tokopedia-lib
Version: 0.0.1
Summary: A simple package named bytedance_shoots_tokopedia_lib
Home-page: https://github.com/artifact/bytedance_shoots_tokopedia_lib.git
Author: artifact
Author-email: artifact@example.com
License: UNKNOWN
Platform: UNKNOWN
Classifier: Programming Language :: Python :: 3
Classifier: License :: OSI Approved :: MIT License
Classifier: Operating System :: OS Independent
